geoip2_extras/__init__.py
geoip2_extras/apps.py
geoip2_extras/middleware.py
geoip2_extras/settings.py
django_geoip2_extras-4.1.dist-info/LICENSE
django_geoip2_extras-4.1.dist-info/METADATA
django_geoip2_extras-4.1.dist-info/WHEEL
django_geoip2_extras-4.1.dist-info/RECORD
