Metadata-Version: 2.1
Name: django-geoip2-extras
Version: 4.1
Summary: Additional functionality using the GeoIP2 database.
Home-page: https://github.com/yunojuno/django-geoip2-extras
License: MIT
Author: YunoJuno
Author-email: code@yunojuno.com
Maintainer: YunoJuno
Maintainer-email: code@yunojuno.com
Requires-Python: >=3.8,<4.0
Classifier: Environment :: Web Environment
Classifier: Framework :: Django :: 3.2
Classifier: Framework :: Django :: 4.0
Classifier: Framework :: Django :: 4.1
Classifier: Framework :: Django :: 4.2
Classifier: Framework :: Django :: 5.0
Classifier: License :: OSI Approved :: MIT License
Classifier: Operating System :: OS Independent
Classifier: Programming Language :: Python :: 3
Classifier: Programming Language :: Python :: 3.8
Classifier: Programming Language :: Python :: 3.9
Classifier: Programming Language :: Python :: 3.10
Classifier: Programming Language :: Python :: 3.11
Classifier: Programming Language :: Python :: 3 :: Only
Classifier: Programming Language :: Python :: 3.12
Requires-Dist: django (>=3.2,<6.0)
Requires-Dist: geoip2 (>=3.0.0,<4.0.0)
Project-URL: Repository, https://github.com/yunojuno/django-geoip2-extras
